{
  "packId": "base.recipes.v1",
  "version": 1,
  "recipes": [
    {
      "id": "rockSorterFractions",
      "label": "Rock Sorter Fractions",
      "tier": 1,
      "discipline": "sorting",
      "station": "processingBay",
      "unlock": { "kind": "starter", "id": "starter.bootstrap" },
      "summary": "Sort mined rubble into core asteroid feedstocks.",
      "processId": "rockSorter",
      "inputs": { "rubble": 10 },
      "outputs": {
        "silicaSand": 4,
        "ironOre": 2,
        "waterIce": 2,
        "co2Ice": 1,
        "carbonRock": 0.6,
        "slagWaste": 0.4
      },
      "tags": ["sorting", "starter"]
    },
    {
      "id": "iceMelterHydration",
      "label": "Ice Melter Hydration",
      "tier": 1,
      "discipline": "hydration",
      "station": "processingBay",
      "unlock": { "kind": "starter", "id": "starter.bootstrap" },
      "summary": "Convert harvested water ice to liquid water feedstock.",
      "processId": "iceMelter",
      "inputs": { "waterIce": 1 },
      "outputs": { "water": 1 },
      "tags": ["hydrogen", "starter"]
    },
    {
      "id": "electrolyzerSplit",
      "label": "Electrolyzer Split",
      "tier": 2,
      "discipline": "electrochemistry",
      "station": "electrochemLab",
      "unlock": { "kind": "quest", "id": "quest.main.learningToCharge" },
      "summary": "Split liquid water into neutral hydrogen and oxygen gas.",
      "processId": "electrolyzer",
      "inputs": { "water": 1 },
      "outputs": { "hydrogenNeutral": 2, "oxygenGas": 1 },
      "tags": ["hydrogen", "energy"]
    },
    {
      "id": "ionizerPlasma",
      "label": "Ionizer Plasma",
      "tier": 3,
      "discipline": "plasmaSystems",
      "station": "plasmaBay",
      "unlock": { "kind": "research", "id": "research.plasmaContainmentI" },
      "summary": "Ionize neutral hydrogen for plasma containment loops.",
      "processId": "ionizer",
      "inputs": { "hydrogenNeutral": 8 },
      "outputs": { "hydrogenIonized": 8 },
      "tags": ["hydrogen", "plasma"]
    },
    {
      "id": "co2SublimatorGas",
      "label": "CO2 Sublimator Gas",
      "tier": 1,
      "discipline": "atmospherics",
      "station": "atmosphericsBay",
      "unlock": { "kind": "starter", "id": "starter.bootstrap" },
      "summary": "Sublimate CO2 ice to gaseous feedstock.",
      "processId": "co2Sublimator",
      "inputs": { "co2Ice": 1 },
      "outputs": { "co2Gas": 1 },
      "tags": ["refining", "atmospherics"]
    },
    {
      "id": "carbonRefinerProduct",
      "label": "Carbon Refiner Product",
      "tier": 1,
      "discipline": "carbonRefining",
      "station": "metallurgyBay",
      "unlock": { "kind": "starter", "id": "starter.bootstrap" },
      "summary": "Refine carbon-rich rock into pure carbon feedstock.",
      "processId": "carbonRefiner",
      "inputs": { "carbonRock": 1 },
      "outputs": { "carbon": 1 },
      "tags": ["refining", "metallurgy"]
    },
    {
      "id": "blastFurnaceIron",
      "label": "Blast Furnace Iron",
      "tier": 2,
      "discipline": "metallurgy",
      "station": "metallurgyBay",
      "unlock": { "kind": "quest", "id": "quest.main.oreToMetal" },
      "summary": "Reduce iron ore to iron metal and CO byproduct.",
      "processId": "blastFurnace",
      "inputs": { "ironOre": 1, "carbon": 3 },
      "outputs": { "ironMetal": 2, "coGas": 3 },
      "tags": ["refining", "metallurgy"]
    },
    {
      "id": "glassForgePanels",
      "label": "Glass Forge Panels",
      "tier": 2,
      "discipline": "glassworking",
      "station": "fabricationBay",
      "unlock": { "kind": "research", "id": "research.fabricationGlassI" },
      "summary": "Fuse silica into structural glass panels.",
      "processId": "glassForge",
      "inputs": { "silicaSand": 3 },
      "outputs": { "glass": 1 },
      "tags": ["manufacturing", "construction"]
    },
    {
      "id": "steelMillBeams",
      "label": "Steel Mill Beams",
      "tier": 3,
      "discipline": "metallurgy",
      "station": "metallurgyBay",
      "unlock": { "kind": "research", "id": "research.metallurgyI" },
      "summary": "Alloy iron and carbon into structural steel beams.",
      "processId": "steelMill",
      "inputs": { "ironMetal": 2, "carbon": 0.1 },
      "outputs": { "steel": 2 },
      "tags": ["manufacturing", "construction"]
    },
    {
      "id": "greenhouseCellulose",
      "label": "Greenhouse Cellulose",
      "tier": 2,
      "discipline": "bioprocessing",
      "station": "bioLab",
      "unlock": { "kind": "research", "id": "research.bioprocessingI" },
      "summary": "Convert CO2 and water into cellulose and oxygen.",
      "processId": "greenhouse",
      "inputs": { "co2Gas": 6, "water": 5 },
      "outputs": { "cellulose": 1, "oxygenGas": 6 },
      "tags": ["bio", "manufacturing"]
    },
    {
      "id": "woodWorkshopPlanks",
      "label": "Wood Workshop Planks",
      "tier": 3,
      "discipline": "woodcraft",
      "station": "fabricationBay",
      "unlock": { "kind": "research", "id": "research.biofabricationI" },
      "summary": "Compress cellulose stock into wood planks.",
      "processId": "woodWorkshop",
      "inputs": { "cellulose": 5 },
      "outputs": { "wood": 1 },
      "tags": ["bio", "construction"]
    }
  ]
}
